src/fifo.v
module fifo #(parameter WIDTH = 8, parameter LOGDEPTH = 3) (
    input clk,
    input reset,

    input enq_val,
    input [WIDTH-1:0] enq_data,
    output enq_rdy,

    output deq_val,
    output [WIDTH-1:0] deq_data,
    input deq_rdy

);

localparam DEPTH = (1 << LOGDEPTH);

reg [WIDTH-1:0] buffer [DEPTH-1:0];
reg [LOGDEPTH-1:0] rptr, wptr;

reg [LOGDEPTH:0] count;

wire full;
wire empty;

assign full = (count == DEPTH);
assign empty = (count == 0);
assign enq_rdy = !full;
assign deq_val = !empty;
assign deq_data = buffer[rptr];

wire enq_time = enq_val & enq_rdy;
wire deq_time = deq_val & deq_rdy;

integer i;
initial begin

  for (i = 0; i < DEPTH; i = i + 1) begin
    buffer[i] = 0;
  end

  rptr = 0;
  wptr = 0;
  count = 0;

end

always @(posedge clk) begin
  if (reset) begin
    for (i = 0; i < DEPTH; i = i + 1) begin
      buffer[i] <= 0;
    end
    rptr <= 0;
    wptr <= 0;
    count <= 0;
  end else begin
    if (enq_time) begin
      buffer[wptr] <= enq_data;
      if (wptr == (DEPTH - 1))
        wptr <= 0;
      else
        wptr <= wptr + 1;
    end

    if (deq_time) begin
      if (rptr == (DEPTH - 1))
        rptr <= 0;
      else
        rptr <= rptr + 1;
    end

    case ({enq_time, deq_time})
      2'b10: count <= count + 1;
      2'b01: count <= count - 1;
      default: count <= count;
    endcase
  end
end

endmodule

sim/fifo_tb.v
`timescale 1ns/1ps

module fifo_tb();

  // Parameters
  localparam WIDTH = 8;
  localparam LOGDEPTH = 3; // depth = 8

  reg clk;
  reg reset;

  reg enq_val;
  reg [WIDTH-1:0] enq_data;
  wire enq_rdy;

  wire deq_val;
  wire [WIDTH-1:0] deq_data;
  reg deq_rdy;

  // Instantiate 
  fifo #(.WIDTH(WIDTH), .LOGDEPTH(LOGDEPTH)) dut (
    .clk(clk),
    .reset(reset),
    .enq_val(enq_val),
    .enq_data(enq_data),
    .enq_rdy(enq_rdy),
    .deq_val(deq_val),
    .deq_data(deq_data),
    .deq_rdy(deq_rdy)
  );

  initial clk = 0;
  always #5 clk = ~clk; // 100MHz clock (10ns period)

  integer i;
  reg [WIDTH-1:0] expected_value;

  initial begin
    $dumpfile("fifo_tb.vcd"); // Dump waves
    $dumpvars(0, fifo_tb);

    enq_val = 0;
    enq_data = 0;
    deq_rdy = 0;
    reset = 1;
    #20;
    reset = 0;

    for (i = 0; i < 8; i = i + 1) begin
      @(negedge clk);
      if (enq_rdy) begin
        enq_val = 1;
        enq_data = i + 8'hA0; // some recognizable values
        $display("[%0t] Enqueue: %h", $time, enq_data);
      end
      @(negedge clk);
      enq_val = 0;
    end

    repeat (3) @(negedge clk);

    deq_rdy = 1;
    for (i = 0; i < 8; i = i + 1) begin
      @(posedge clk);
      if (deq_val) begin
        expected_value = i + 8'hA0;
        if (deq_data !== expected_value)
          $display("[%0t] ERROR: Expected %h, got %h", $time, expected_value, deq_data);
        else
          $display("[%0t] Dequeue: %h (PASSED)", $time, deq_data);
      end
    end

    deq_rdy = 0;
    @(negedge clk);
    $display("[%0t] ALL TESTS PASSED", $time);
    $finish;
  end

endmodule

sim/fifo_tb.vcd
$date
	Wed Oct 22 23:13:39 2025
$end
$version
	Icarus Verilog
$end
$timescale
	1ps
$end
$scope module fifo_tb $end
$var wire 1 ! enq_rdy $end
$var wire 1 " deq_val $end
$var wire 8 # deq_data [7:0] $end
$var parameter 32 $ LOGDEPTH $end
$var parameter 32 % WIDTH $end
$var reg 1 & clk $end
$var reg 1 ' deq_rdy $end
$var reg 8 ( enq_data [7:0] $end
$var reg 1 ) enq_val $end
$var reg 8 * expected_value [7:0] $end
$var reg 1 + reset $end
$var integer 32 , i [31:0] $end
$scope module dut $end
$var wire 1 & clk $end
$var wire 8 - deq_data [7:0] $end
$var wire 1 ' deq_rdy $end
$var wire 1 . deq_time $end
$var wire 8 / enq_data [7:0] $end
$var wire 1 0 enq_time $end
$var wire 1 ) enq_val $end
$var wire 1 + reset $end
$var wire 1 1 full $end
$var wire 1 ! enq_rdy $end
$var wire 1 2 empty $end
$var wire 1 " deq_val $end
$var parameter 35 3 DEPTH $end
$var parameter 32 4 LOGDEPTH $end
$var parameter 32 5 WIDTH $end
$var reg 4 6 count [3:0] $end
$var reg 3 7 rptr [2:0] $end
$var reg 3 8 wptr [2:0] $end
$var integer 32 9 i [31:0] $end
$upscope $end
$upscope $end
$enddefinitions $end
$comment Show the parameter values. $end
$dumpall
b1000 5
b11 4
b1000 3
b1000 %
b11 $
$end
#0
$dumpvars
b1000 9
b0 8
b0 7
b0 6
12
01
00
b0 /
0.
b0 -
bx ,
1+
bx *
0)
b0 (
0'
0&
b0 #
0"
1!
$end
#5000
b1000 9
1&
#10000
0&
#15000
b1000 9
1&
#20000
10
b10100000 (
b10100000 /
1)
0&
b0 ,
0+
#25000
1"
02
b1 6
b1 8
b10100000 #
b10100000 -
1&
#30000
00
b1 ,
0)
0&
#35000
1&
#40000
10
b10100001 (
b10100001 /
1)
0&
#45000
b10 6
b10 8
1&
#50000
00
b10 ,
0)
0&
#55000
1&
#60000
10
b10100010 (
b10100010 /
1)
0&
#65000
b11 6
b11 8
1&
#70000
00
b11 ,
0)
0&
#75000
1&
#80000
10
b10100011 (
b10100011 /
1)
0&
#85000
b100 6
b100 8
1&
#90000
00
b100 ,
0)
0&
#95000
1&
#100000
10
b10100100 (
b10100100 /
1)
0&
#105000
b101 6
b101 8
1&
#110000
00
b101 ,
0)
0&
#115000
1&
#120000
10
b10100101 (
b10100101 /
1)
0&
#125000
b110 6
b110 8
1&
#130000
00
b110 ,
0)
0&
#135000
1&
#140000
10
b10100110 (
b10100110 /
1)
0&
#145000
b111 6
b111 8
1&
#150000
00
b111 ,
0)
0&
#155000
1&
#160000
10
b10100111 (
b10100111 /
1)
0&
#165000
00
0!
11
b1000 6
b0 8
1&
#170000
b1000 ,
0)
0&
#175000
1&
#180000
0&
#185000
1&
#190000
0&
#195000
1&
#200000
1.
b0 ,
1'
0&
#205000
1!
01
b111 6
b10100001 #
b10100001 -
b1 7
b1 ,
b10100000 *
1&
#210000
0&
#215000
b110 6
b10100010 #
b10100010 -
b10 7
b10 ,
b10100001 *
1&
#220000
0&
#225000
b101 6
b10100011 #
b10100011 -
b11 7
b11 ,
b10100010 *
1&
#230000
0&
#235000
b100 6
b10100100 #
b10100100 -
b100 7
b100 ,
b10100011 *
1&
#240000
0&
#245000
b11 6
b10100101 #
b10100101 -
b101 7
b101 ,
b10100100 *
1&
#250000
0&
#255000
b10 6
b10100110 #
b10100110 -
b110 7
b110 ,
b10100101 *
1&
#260000
0&
#265000
b1 6
b10100111 #
b10100111 -
b111 7
b111 ,
b10100110 *
1&
#270000
0&
#275000
0"
12
b0 6
b10100000 #
b10100000 -
b0 7
0.
0'
b1000 ,
b10100111 *
1&
